setup.cfg
setup.py
meet/__init__.py
meet/main.py
meet.egg-info/PKG-INFO
meet.egg-info/SOURCES.txt
meet.egg-info/dependency_links.txt
meet.egg-info/entry_points.txt
meet.egg-info/not-zip-safe
meet.egg-info/requires.txt
meet.egg-info/top_level.txt
meet/config/__init__.py
meet/config/config.py
meet/functions/__init__.py
meet/functions/functions.py
meet/google/__init__.py
meet/google/gcalendar.py
meet/interface/__init__.py
meet/interface/api.py
meet/terminal/__init__.py
meet/terminal/terminal.py